[
        {
            "id": 2,
            "x": 5.0239057540893559,
            "y": 2.8630905151367189
        },
        {
            "id": 3,
            "x": -7.104053020477295,
            "y": 1.9784164428710938
        },
        {
            "id": 1,
            "x": 5.283291816711426,
            "y": -5.031489372253418
        },
        {
            "id": 1,
            "x": -5.996945381164551,
            "y": -6.625856399536133
        },
        {
            "id": 2,
            "x": -1.5403646230697632,
            "y": 3.9780445098876955
        },
        {
            "id": 3,
            "x": 1.8608227968215943,
            "y": -5.219371795654297
        },
        {
            "id": 1,
            "x": -0.7873810529708862,
            "y": -2.7700700759887697
        }
    ]